seatdata/__init__.py
seatdata/client.py
seatdata/exceptions.py
seatdata_sdk-0.3.0.dist-info/licenses/LICENSE
seatdata_sdk-0.3.0.dist-info/METADATA
seatdata_sdk-0.3.0.dist-info/WHEEL
seatdata_sdk-0.3.0.dist-info/top_level.txt
seatdata_sdk-0.3.0.dist-info/RECORD
